[{"line":2,"elements":[{"line":4,"name":"","description":"","type":"background","keyword":"Background","steps":[{"result":{"duration":4329841200,"status":"passed"},"line":5,"name":"user on flight tab","match":{"location":"stepdefs.dicoSteps.user_on_flight_tab()"},"keyword":"Given "}]},{"start_timestamp":"2025-10-24T08:05:53.045Z","before":[{"result":{"duration":1232030400,"status":"passed"},"match":{"location":"hooks.hook.setup()"}}],"line":17,"name":"User Checkout with single trip onboadring","description":"","id":"flight-checkout;user-checkout-with-single-trip-onboadring;;2","after":[{"result":{"duration":302122700,"status":"passed"},"match":{"location":"hooks.hook.teardown()"}}],"type":"scenario","keyword":"Scenario Outline","steps":[{"result":{"duration":3686233300,"status":"passed"},"line":8,"name":"user had input flight detail","match":{"location":"stepdefs.dicoSteps.user_had_input_flight_detail()"},"keyword":"When "},{"result":{"duration":4998000,"status":"passed"},"line":9,"name":"user sets passengers adult 1 child 0 infant 0","match":{"arguments":[{"val":"1","offset":27},{"val":"0","offset":35},{"val":"0","offset":44}],"location":"stepdefs.dicoSteps.user_sets_passengers(java.lang.Integer,java.lang.Integer,java.lang.Integer)"},"keyword":"And "},{"result":{"duration":3249948600,"status":"passed"},"line":10,"name":"user sets flight category \"economy\"","match":{"arguments":[{"val":"\"economy\"","offset":26}],"location":"stepdefs.dicoSteps.userSetsFlightCategory(java.lang.String)"},"keyword":"And "},{"result":{"duration":5624718100,"status":"passed"},"line":11,"name":"user search and select cheapest flight of \"Indonesia AirAsia\"","match":{"arguments":[{"val":"\"Indonesia AirAsia\"","offset":42}],"location":"stepdefs.dicoSteps.userSearchFlight(java.lang.String)"},"keyword":"And "},{"result":{"duration":21808611800,"status":"passed"},"line":12,"name":"user fill data on booking information page","match":{"location":"stepdefs.bookingInfoSteps.user_fill_data_on_booking_information_page()"},"keyword":"And "},{"result":{"duration":443441900,"status":"passed"},"line":13,"name":"user validate the detail order on payment check page","match":{"location":"stepdefs.paymentCheckSteps.user_click_payment_button()"},"keyword":"Then "}],"tags":[{"name":"@checkout"}]},{"line":4,"name":"","description":"","type":"background","keyword":"Background","steps":[{"result":{"duration":4071617900,"status":"passed"},"line":5,"name":"user on flight tab","match":{"location":"stepdefs.dicoSteps.user_on_flight_tab()"},"keyword":"Given "}]},{"start_timestamp":"2025-10-24T08:06:33.804Z","before":[{"result":{"duration":1224057100,"status":"passed"},"match":{"location":"hooks.hook.setup()"}}],"line":18,"name":"User Checkout with single trip onboadring","description":"","id":"flight-checkout;user-checkout-with-single-trip-onboadring;;3","after":[{"result":{"duration":246875700,"status":"passed"},"match":{"location":"hooks.hook.teardown()"}}],"type":"scenario","keyword":"Scenario Outline","steps":[{"result":{"duration":4051814700,"status":"passed"},"line":8,"name":"user had input flight detail","match":{"location":"stepdefs.dicoSteps.user_had_input_flight_detail()"},"keyword":"When "},{"result":{"duration":498462500,"status":"passed"},"line":9,"name":"user sets passengers adult 2 child 1 infant 1","match":{"arguments":[{"val":"2","offset":27},{"val":"1","offset":35},{"val":"1","offset":44}],"location":"stepdefs.dicoSteps.user_sets_passengers(java.lang.Integer,java.lang.Integer,java.lang.Integer)"},"keyword":"And "},{"result":{"duration":2327534500,"status":"passed"},"line":10,"name":"user sets flight category \"economy\"","match":{"arguments":[{"val":"\"economy\"","offset":26}],"location":"stepdefs.dicoSteps.userSetsFlightCategory(java.lang.String)"},"keyword":"And "},{"result":{"duration":5103350600,"status":"passed"},"line":11,"name":"user search and select cheapest flight of \"Indonesia AirAsia\"","match":{"arguments":[{"val":"\"Indonesia AirAsia\"","offset":42}],"location":"stepdefs.dicoSteps.userSearchFlight(java.lang.String)"},"keyword":"And "},{"result":{"duration":48063054700,"status":"passed"},"line":12,"name":"user fill data on booking information page","match":{"location":"stepdefs.bookingInfoSteps.user_fill_data_on_booking_information_page()"},"keyword":"And "},{"result":{"duration":126140900,"status":"passed"},"line":13,"name":"user validate the detail order on payment check page","match":{"location":"stepdefs.paymentCheckSteps.user_click_payment_button()"},"keyword":"Then "}],"tags":[{"name":"@checkout"}]},{"line":4,"name":"","description":"","type":"background","keyword":"Background","steps":[{"result":{"duration":4431350700,"status":"passed"},"line":5,"name":"user on flight tab","match":{"location":"stepdefs.dicoSteps.user_on_flight_tab()"},"keyword":"Given "}]},{"start_timestamp":"2025-10-24T08:07:39.529Z","before":[{"result":{"duration":1149755600,"status":"passed"},"match":{"location":"hooks.hook.setup()"}}],"line":19,"name":"User Checkout with single trip onboadring","description":"","id":"flight-checkout;user-checkout-with-single-trip-onboadring;;4","after":[{"result":{"duration":287262200,"status":"passed"},"match":{"location":"hooks.hook.teardown()"}}],"type":"scenario","keyword":"Scenario Outline","steps":[{"result":{"duration":4874811600,"status":"passed"},"line":8,"name":"user had input flight detail","match":{"location":"stepdefs.dicoSteps.user_had_input_flight_detail()"},"keyword":"When "},{"result":{"duration":479183600,"status":"passed"},"line":9,"name":"user sets passengers adult 1 child 2 infant 1","match":{"arguments":[{"val":"1","offset":27},{"val":"2","offset":35},{"val":"1","offset":44}],"location":"stepdefs.dicoSteps.user_sets_passengers(java.lang.Integer,java.lang.Integer,java.lang.Integer)"},"keyword":"And "},{"result":{"duration":2223605100,"status":"passed"},"line":10,"name":"user sets flight category \"business\"","match":{"arguments":[{"val":"\"business\"","offset":26}],"location":"stepdefs.dicoSteps.userSetsFlightCategory(java.lang.String)"},"keyword":"And "},{"result":{"duration":4499578200,"status":"passed"},"line":11,"name":"user search and select cheapest flight of \"Garuda Indonesia\"","match":{"arguments":[{"val":"\"Garuda Indonesia\"","offset":42}],"location":"stepdefs.dicoSteps.userSearchFlight(java.lang.String)"},"keyword":"And "},{"result":{"duration":24505158600,"status":"passed"},"line":12,"name":"user fill data on booking information page","match":{"location":"stepdefs.bookingInfoSteps.user_fill_data_on_booking_information_page()"},"keyword":"And "},{"result":{"duration":162968400,"status":"passed"},"line":13,"name":"user validate the detail order on payment check page","match":{"location":"stepdefs.paymentCheckSteps.user_click_payment_button()"},"keyword":"Then "}],"tags":[{"name":"@checkout"}]}],"name":"Flight Checkout","description":"","id":"flight-checkout","keyword":"Feature","uri":"file:src/test/resources/features/checkout.feature","tags":[{"name":"@checkout","type":"Tag","location":{"line":1,"column":1}}]}]